README.md
setup.py
app/__init__.py
app/appengine_config.py
app/server.py
restae/__init__.py
restae/conf.py
restae/decorators.py
restae/exceptions.py
restae/handlers.py
restae/handlers_test.py
restae/helpers.py
restae/management.py
restae/middleware.py
restae/middleware_test.py
restae/pagination.py
restae/response.py
restae/router.py
restae/router_test.py
restae/serializers.py
restae/serializers_test.py
restae.egg-info/PKG-INFO
restae.egg-info/SOURCES.txt
restae.egg-info/dependency_links.txt
restae.egg-info/entry_points.txt
restae.egg-info/not-zip-safe
restae.egg-info/top_level.txt